[
            {   
                "id":1,
                "nameConference":"Fin de la pobreza",
                "nameSpeaker":"Que te importa",
                "date":"22/10/2018",
                "hour":"10:00",
                "image":"https://farm2.staticflickr.com/1940/31019450958_e0f66730d0_k.jpg"
            },
            {
                "id":2,"nameConference":"Hambre cero",
                "nameSpeaker":"Iovany Girón Moreno",
                "date":"22/10/2018",
                "hour":"11:00",
                "image":"https://farm2.staticflickr.com/1964/43080890430_59fce96661_k.jpg"
            },
            {
                "id":3,"nameConference":"Salud y bienestar",
                "nameSpeaker":"Javier Chavez Flores",
                "date":"22/10/2018",
                "hour":"12:00",
                "image":"https://farm2.staticflickr.com/1919/44172525004_81e152a20e_k.jpg"
            },
            {
                "id":4,"nameConference":"Educación de calidad",
                "nameSpeaker":"Sanda I. Brito Aguilar",
                "date":"22/10/2018",
                "hour":"13:00",
                "image":"https://farm2.staticflickr.com/1945/43080889370_750520d61a_k.jpg"
            },
            {
                "id":5,"nameConference":"Igualdad de género",
                "nameSpeaker":"Fabiola V. Lara Treviño",
                "date":"22/10/2018",
                "hour":"15:00",
                "image":"https://farm2.staticflickr.com/1962/43080892120_1de65681e5_k.jpg"
            },
            {
                "id":6,"nameConference":"Agua limpia y saneamiento",
                "nameSpeaker":"Luis Alberto",
                "date":"23/10/2018",
                "hour":"16:00",
                "image":"https://farm2.staticflickr.com/1942/31019451518_d907adbbdd_k.jpg"
            },
            {
                "id":7,"nameConference":"Energía asequible y no contaminante",
                "nameSpeaker":"Jesus Antonio",
                "date":"23/10/2018",
                "hour":"17:00",
                "image":"https://farm2.staticflickr.com/1940/31019450328_7db3aac7f0_k.jpg"
            },
            {
                "id":8,"nameConference":"Trabajo decente y crecimiento económico",
                "nameSpeaker":"Maria Isabel",
                "date":"23/10/2018",
                "hour":"18:00",
                "image":"https://farm2.staticflickr.com/1919/44172521674_88d29aec7e_k.jpg"
            }
]